mac2win_zip/__init__.py
mac2win_zip/cli.py
mac2win_zip-1.0.1.dist-info/METADATA
mac2win_zip-1.0.1.dist-info/WHEEL
mac2win_zip-1.0.1.dist-info/entry_points.txt
mac2win_zip-1.0.1.dist-info/licenses/LICENSE
mac2win_zip-1.0.1.dist-info/RECORD
