Metadata-Version: 2.4
Name: mac2win-zip
Version: 1.0.1
Summary: Create Windows-compatible ZIP files from macOS
Project-URL: Homepage, https://github.com/Wordbe/mac2win-zip
Project-URL: Repository, https://github.com/Wordbe/mac2win-zip
Project-URL: Issues, https://github.com/Wordbe/mac2win-zip/issues
Author: mac2win-zip contributors
License: MIT License
License-File: LICENSE
Keywords: macos,nfc,nfd,unicode,windows,zip
Classifier: Development Status :: 4 - Beta
Classifier: Intended Audience :: Developers
Classifier: License :: OSI Approved :: MIT License
Classifier: Operating System :: MacOS
Classifier: Programming Language :: Python :: 3
Classifier: Programming Language :: Python :: 3.8
Classifier: Programming Language :: Python :: 3.9
Classifier: Programming Language :: Python :: 3.10
Classifier: Programming Language :: Python :: 3.11
Classifier: Programming Language :: Python :: 3.12
Classifier: Topic :: System :: Archiving :: Compression
Requires-Python: >=3.8
Provides-Extra: dev
Requires-Dist: black>=23.0.0; extra == 'dev'
Requires-Dist: pytest-cov>=4.0.0; extra == 'dev'
Requires-Dist: pytest>=7.0.0; extra == 'dev'
Requires-Dist: ruff>=0.1.0; extra == 'dev'
